securitycore/__init__.py
securitycore/_internal/__init__.py
securitycore/_internal/constants.py
securitycore/_internal/error.py
securitycore/_internal/patterns.py
securitycore/_internal/regexes.py
securitycore/analysis/__init__.py
securitycore/analysis/entropy.py
securitycore/analysis/password_analyzer.py
securitycore/audit/__init__.py
securitycore/audit/audit_logger.py
securitycore/audit/json_logger.py
securitycore/crypto/__init__.py
securitycore/crypto/crypto_utils.py
securitycore/crypto/keygen.py
securitycore/crypto/tokens.py
securitycore/protection/__init__.py
securitycore/protection/input_sanitizer.py
securitycore/protection/path_safety.py
securitycore/protection/sql.py
securitycore/protection/xss.py
securitycore/utils/__init__.py
securitycore/utils/helpers.py
securitycore/utils/patterns.py
securitycore/validators/__init__.py
securitycore/validators/email_validator.py
securitycore/validators/ip_validator.py
securitycore/validators/password_validator.py
securitycore/validators/url_validator.py
securitycore-1.0.3.dist-info/licenses/LICENSE
securitycore-1.0.3.dist-info/METADATA
securitycore-1.0.3.dist-info/WHEEL
securitycore-1.0.3.dist-info/top_level.txt
securitycore-1.0.3.dist-info/RECORD
