Metadata-Version: 2.4
Name: securitycore
Version: 1.0.3
Summary: Модульная библиотека для анализа, защиты и валидации данных
Author-email: Mihhail327 <mixa-amr@hotmail.com>
License: MIT
Project-URL: Homepage, https://github.com/Mihhail327/SecurityCore
Project-URL: Repository, https://github.com/Mihhail327/SecurityCore
Project-URL: Issues, https://github.com/Mihhail327/SecurityCore/issues
Keywords: security,validation,cryptography,data-protection
Classifier: Programming Language :: Python :: 3.10
Classifier: Programming Language :: Python :: 3.11
Classifier: Programming Language :: Python :: 3.12
Classifier: Programming Language :: Python :: 3.13
Classifier: License :: OSI Approved :: MIT License
Classifier: Operating System :: OS Independent
Classifier: Topic :: Security
Classifier: Topic :: Software Development :: Libraries
Classifier: Intended Audience :: Developers
Requires-Python: >=3.10
License-File: LICENSE
Requires-Dist: cryptography>=41.0.0
Provides-Extra: dev
Requires-Dist: pytest>=7.0.0; extra == "dev"
Dynamic: license-file
